powerflex_monitoring/VERSION
powerflex_monitoring/__init__.py
powerflex_monitoring/diagnostic_recorder.py
powerflex_monitoring/format_exception.py
powerflex_monitoring/health_check.py
powerflex_monitoring/monitoring.py
powerflex_monitoring/nats_health_check.py
powerflex_monitoring/prometheus_metrics.py
powerflex_monitoring/py.typed
powerflex_monitoring/ready_check.py
powerflex_monitoring/redis_health_check.py
powerflex_monitoring/server_base.py
powerflex_monitoring/wait_for_service_ready.py
powerflex_monitoring-1.8.1.dist-info/METADATA
powerflex_monitoring-1.8.1.dist-info/WHEEL
powerflex_monitoring-1.8.1.dist-info/RECORD
