Metadata-Version: 2.3
Name: powerflex-monitoring
Version: 1.8.1
Summary: Tools to assist in monitoring a Python service.
Keywords: monitoring,powerflex,python
Author: Powerflex
Maintainer: Powerflex
Requires-Python: >=3.8
Classifier: Intended Audience :: Developers
Classifier: Operating System :: Unix
Classifier: Operating System :: POSIX
Classifier: Programming Language :: Python
Classifier: Programming Language :: Python :: 3
Classifier: Programming Language :: Python :: 3.8
Classifier: Programming Language :: Python :: 3.9
Classifier: Programming Language :: Python :: 3.10
Classifier: Programming Language :: Python :: 3.11
Classifier: Programming Language :: Python :: Implementation :: CPython
Classifier: Programming Language :: Python :: Implementation :: PyPy
Provides-Extra: pydantic2
Requires-Dist: backoff (>=2)
Requires-Dist: colorlog (>=6)
Requires-Dist: nats-py (>=2.2.0)
Requires-Dist: prometheus_client (>=0.14)
Requires-Dist: pydantic (>=1.9)
Requires-Dist: pydantic_settings (>=2) ; extra == "pydantic2"
Requires-Dist: redis (>=4.3.4)
Requires-Dist: requests (>=2)
Requires-Dist: starlette (>=0.20)
Requires-Dist: types-requests (>=2)
Requires-Dist: uvicorn (>=0.18)
Project-URL: Homepage, https://github.com/edf-re/powerflex_python_monitoring
Project-URL: Issue Tracker, https://github.com/edf-re/powerflex_python_monitoring/issues
